pyPreservica/__init__.py
pyPreservica/adminAPI.py
pyPreservica/authorityAPI.py
pyPreservica/common.py
pyPreservica/contentAPI.py
pyPreservica/entityAPI.py
pyPreservica/mdformsAPI.py
pyPreservica/monitorAPI.py
pyPreservica/opex.py
pyPreservica/parAPI.py
pyPreservica/retentionAPI.py
pyPreservica/settingsAPI.py
pyPreservica/uploadAPI.py
pyPreservica/webHooksAPI.py
pyPreservica/workflowAPI.py
pypreservica-3.4.0.dist-info/licenses/LICENSE.txt
pypreservica-3.4.0.dist-info/METADATA
pypreservica-3.4.0.dist-info/WHEEL
pypreservica-3.4.0.dist-info/top_level.txt
pypreservica-3.4.0.dist-info/RECORD
