Metadata-Version: 2.4
Name: pyPreservica
Version: 3.4.0
Summary: Python library for the Preservica API
Home-page: https://pypreservica.readthedocs.io/
Author: James Carr
Author-email: drjamescarr@gmail.com
License: Apache License 2.0
Project-URL: Documentation, https://pypreservica.readthedocs.io
Project-URL: Source, https://github.com/carj/pyPreservica
Project-URL: Discussion Forum, https://groups.google.com/g/pypreservica
Keywords: Preservica API Preservation
Classifier: Programming Language :: Python :: 3
Classifier: Programming Language :: Python :: 3.8
Classifier: Programming Language :: Python :: 3.9
Classifier: Programming Language :: Python :: 3.10
Classifier: Programming Language :: Python :: 3.11
Classifier: Programming Language :: Python :: 3.12
Classifier: Programming Language :: Python :: 3.13
Classifier: Operating System :: OS Independent
Classifier: Topic :: System :: Archiving
License-File: LICENSE.txt
Requires-Dist: requests
Requires-Dist: urllib3
Requires-Dist: certifi
Requires-Dist: boto3>=1.38.0
Requires-Dist: botocore>=1.38.0
Requires-Dist: s3transfer
Requires-Dist: azure-storage-blob
Requires-Dist: tqdm
Requires-Dist: pyotp
Requires-Dist: python-dateutil
Dynamic: author
Dynamic: author-email
Dynamic: classifier
Dynamic: description
Dynamic: description-content-type
Dynamic: home-page
Dynamic: keywords
Dynamic: license
Dynamic: license-file
Dynamic: project-url
Dynamic: requires-dist
Dynamic: summary
